LICENSE.txt
README.rst
setup.cfg
setup.py
wizvolcano/__init__.py
wizvolcano/volcano.py
wizvolcano.egg-info/PKG-INFO
wizvolcano.egg-info/SOURCES.txt
wizvolcano.egg-info/dependency_links.txt
wizvolcano.egg-info/top_level.txt